pyLatch/__init__.py
pyLatch/pyLatch.py
pyLatch-0.1.0.dist-info/LICENSE
pyLatch-0.1.0.dist-info/METADATA
pyLatch-0.1.0.dist-info/WHEEL
pyLatch-0.1.0.dist-info/top_level.txt
pyLatch-0.1.0.dist-info/RECORD
