Metadata-Version: 2.1
Name: pyLatch
Version: 0.1.0
Summary: A simple and basic API wrapper for Latch written in Python
Home-page: http://github.com/rubegartor/pyLatch
Author: rubegartor
Author-email: rubegartor@gmail.com
License: MIT
Keywords: Latch,Python3,Python,Latch API wrapper,ElevenPaths
Platform: UNKNOWN
Classifier: Programming Language :: Python :: 3
Classifier: License :: OSI Approved :: MIT License
Classifier: Operating System :: OS Independent
